{
  "id": "70cf8c04-d675-46df-805a-c6714c7107e3",
  "prevId": "3c4a451a-30a3-4355-8ac5-f739a7316e81",
  "version": "7",
  "dialect": "postgresql",
  "tables": {
    "public.tonytonyshopper_account": {
      "name": "tonytonyshopper_account",
      "schema": "",
      "columns": {
        "userId": {
          "name": "userId",
          "type": "varchar(255)",
          "primaryKey": false,
          "notNull": true
        },
        "type": {
          "name": "type",
          "type": "varchar(255)",
          "primaryKey": false,
          "notNull": true
        },
        "provider": {
          "name": "provider",
          "type": "varchar(255)",
          "primaryKey": false,
          "notNull": true
        },
        "providerAccountId": {
          "name": "providerAccountId",
          "type": "varchar(255)",
          "primaryKey": false,
          "notNull": true
        },
        "refresh_token": {
          "name": "refresh_token",
          "type": "text",
          "primaryKey": false,
          "notNull": false
        },
        "access_token": {
          "name": "access_token",
          "type": "text",
          "primaryKey": false,
          "notNull": false
        },
        "expires_at": {
          "name": "expires_at",
          "type": "integer",
          "primaryKey": false,
          "notNull": false
        },
        "token_type": {
          "name": "token_type",
          "type": "varchar(255)",
          "primaryKey": false,
          "notNull": false
        },
        "scope": {
          "name": "scope",
          "type": "varchar(255)",
          "primaryKey": false,
          "notNull": false
        },
        "id_token": {
          "name": "id_token",
          "type": "text",
          "primaryKey": false,
          "notNull": false
        },
        "session_state": {
          "name": "session_state",
          "type": "varchar(255)",
          "primaryKey": false,
          "notNull": false
        }
      },
      "indexes": {
        "account_user_id_idx": {
          "name": "account_user_id_idx",
          "columns": [
            {
              "expression": "userId",
              "isExpression": false,
              "asc": true,
              "nulls": "last"
            }
          ],
          "isUnique": false,
          "concurrently": false,
          "method": "btree",
          "with": {}
        }
      },
      "foreignKeys": {
        "tonytonyshopper_account_userId_tonytonyshopper_user_id_fk": {
          "name": "tonytonyshopper_account_userId_tonytonyshopper_user_id_fk",
          "tableFrom": "tonytonyshopper_account",
          "tableTo": "tonytonyshopper_user",
          "columnsFrom": [
            "userId"
          ],
          "columnsTo": [
            "id"
          ],
          "onDelete": "no action",
          "onUpdate": "no action"
        }
      },
      "compositePrimaryKeys": {
        "tonytonyshopper_account_provider_providerAccountId_pk": {
          "name": "tonytonyshopper_account_provider_providerAccountId_pk",
          "columns": [
            "provider",
            "providerAccountId"
          ]
        }
      },
      "uniqueConstraints": {},
      "policies": {},
      "checkConstraints": {},
      "isRLSEnabled": false
    },
    "public.tonytonyshopper_cart_item": {
      "name": "tonytonyshopper_cart_item",
      "schema": "",
      "columns": {
        "userId": {
          "name": "userId",
          "type": "varchar(255)",
          "primaryKey": false,
          "notNull": true
        },
        "productVariantId": {
          "name": "productVariantId",
          "type": "varchar(255)",
          "primaryKey": false,
          "notNull": true
        },
        "quantity": {
          "name": "quantity",
          "type": "integer",
          "primaryKey": false,
          "notNull": true,
          "default": 1
        },
        "createdAt": {
          "name": "createdAt",
          "type": "timestamp with time zone",
          "primaryKey": false,
          "notNull": false,
          "default": "CURRENT_TIMESTAMP"
        }
      },
      "indexes": {},
      "foreignKeys": {
        "tonytonyshopper_cart_item_userId_tonytonyshopper_user_id_fk": {
          "name": "tonytonyshopper_cart_item_userId_tonytonyshopper_user_id_fk",
          "tableFrom": "tonytonyshopper_cart_item",
          "tableTo": "tonytonyshopper_user",
          "columnsFrom": [
            "userId"
          ],
          "columnsTo": [
            "id"
          ],
          "onDelete": "cascade",
          "onUpdate": "no action"
        },
        "tonytonyshopper_cart_item_productVariantId_tonytonyshopper_product_variant_id_fk": {
          "name": "tonytonyshopper_cart_item_productVariantId_tonytonyshopper_product_variant_id_fk",
          "tableFrom": "tonytonyshopper_cart_item",
          "tableTo": "tonytonyshopper_product_variant",
          "columnsFrom": [
            "productVariantId"
          ],
          "columnsTo": [
            "id"
          ],
          "onDelete": "cascade",
          "onUpdate": "no action"
        }
      },
      "compositePrimaryKeys": {
        "tonytonyshopper_cart_item_userId_productVariantId_pk": {
          "name": "tonytonyshopper_cart_item_userId_productVariantId_pk",
          "columns": [
            "userId",
            "productVariantId"
          ]
        }
      },
      "uniqueConstraints": {},
      "policies": {},
      "checkConstraints": {},
      "isRLSEnabled": false
    },
    "public.tonytonyshopper_category": {
      "name": "tonytonyshopper_category",
      "schema": "",
      "columns": {
        "id": {
          "name": "id",
          "type": "varchar(255)",
          "primaryKey": true,
          "notNull": true
        },
        "name": {
          "name": "name",
          "type": "varchar(255)",
          "primaryKey": false,
          "notNull": true
        }
      },
      "indexes": {},
      "foreignKeys": {},
      "compositePrimaryKeys": {},
      "uniqueConstraints": {
        "tonytonyshopper_category_name_unique": {
          "name": "tonytonyshopper_category_name_unique",
          "nullsNotDistinct": false,
          "columns": [
            "name"
          ]
        }
      },
      "policies": {},
      "checkConstraints": {},
      "isRLSEnabled": false
    },
    "public.tonytonyshopper_comment": {
      "name": "tonytonyshopper_comment",
      "schema": "",
      "columns": {
        "id": {
          "name": "id",
          "type": "varchar(255)",
          "primaryKey": true,
          "notNull": true
        },
        "rating": {
          "name": "rating",
          "type": "integer",
          "primaryKey": false,
          "notNull": false
        },
        "text": {
          "name": "text",
          "type": "text",
          "primaryKey": false,
          "notNull": true
        },
        "userId": {
          "name": "userId",
          "type": "varchar(255)",
          "primaryKey": false,
          "notNull": true
        },
        "productId": {
          "name": "productId",
          "type": "varchar(255)",
          "primaryKey": false,
          "notNull": true
        },
        "parentId": {
          "name": "parentId",
          "type": "varchar(255)",
          "primaryKey": false,
          "notNull": false
        },
        "createdAt": {
          "name": "createdAt",
          "type": "timestamp with time zone",
          "primaryKey": false,
          "notNull": false,
          "default": "CURRENT_TIMESTAMP"
        }
      },
      "indexes": {
        "comment_product_id_idx": {
          "name": "comment_product_id_idx",
          "columns": [
            {
              "expression": "productId",
              "isExpression": false,
              "asc": true,
              "nulls": "last"
            }
          ],
          "isUnique": false,
          "concurrently": false,
          "method": "btree",
          "with": {}
        },
        "comment_parent_id_idx": {
          "name": "comment_parent_id_idx",
          "columns": [
            {
              "expression": "parentId",
              "isExpression": false,
              "asc": true,
              "nulls": "last"
            }
          ],
          "isUnique": false,
          "concurrently": false,
          "method": "btree",
          "with": {}
        }
      },
      "foreignKeys": {
        "tonytonyshopper_comment_userId_tonytonyshopper_user_id_fk": {
          "name": "tonytonyshopper_comment_userId_tonytonyshopper_user_id_fk",
          "tableFrom": "tonytonyshopper_comment",
          "tableTo": "tonytonyshopper_user",
          "columnsFrom": [
            "userId"
          ],
          "columnsTo": [
            "id"
          ],
          "onDelete": "cascade",
          "onUpdate": "no action"
        },
        "tonytonyshopper_comment_productId_tonytonyshopper_product_id_fk": {
          "name": "tonytonyshopper_comment_productId_tonytonyshopper_product_id_fk",
          "tableFrom": "tonytonyshopper_comment",
          "tableTo": "tonytonyshopper_product",
          "columnsFrom": [
            "productId"
          ],
          "columnsTo": [
            "id"
          ],
          "onDelete": "cascade",
          "onUpdate": "no action"
        },
        "tonytonyshopper_comment_parentId_tonytonyshopper_comment_id_fk": {
          "name": "tonytonyshopper_comment_parentId_tonytonyshopper_comment_id_fk",
          "tableFrom": "tonytonyshopper_comment",
          "tableTo": "tonytonyshopper_comment",
          "columnsFrom": [
            "parentId"
          ],
          "columnsTo": [
            "id"
          ],
          "onDelete": "cascade",
          "onUpdate": "no action"
        }
      },
      "compositePrimaryKeys": {},
      "uniqueConstraints": {},
      "policies": {},
      "checkConstraints": {},
      "isRLSEnabled": false
    },
    "public.tonytonyshopper_order_item": {
      "name": "tonytonyshopper_order_item",
      "schema": "",
      "columns": {
        "id": {
          "name": "id",
          "type": "varchar(255)",
          "primaryKey": true,
          "notNull": true
        },
        "orderId": {
          "name": "orderId",
          "type": "varchar(255)",
          "primaryKey": false,
          "notNull": true
        },
        "productVariantId": {
          "name": "productVariantId",
          "type": "varchar(255)",
          "primaryKey": false,
          "notNull": true
        },
        "quantity": {
          "name": "quantity",
          "type": "integer",
          "primaryKey": false,
          "notNull": true
        },
        "priceAtPurchase": {
          "name": "priceAtPurchase",
          "type": "numeric(10, 2)",
          "primaryKey": false,
          "notNull": true
        }
      },
      "indexes": {
        "order_item_order_id_idx": {
          "name": "order_item_order_id_idx",
          "columns": [
            {
              "expression": "orderId",
              "isExpression": false,
              "asc": true,
              "nulls": "last"
            }
          ],
          "isUnique": false,
          "concurrently": false,
          "method": "btree",
          "with": {}
        }
      },
      "foreignKeys": {
        "tonytonyshopper_order_item_orderId_tonytonyshopper_order_id_fk": {
          "name": "tonytonyshopper_order_item_orderId_tonytonyshopper_order_id_fk",
          "tableFrom": "tonytonyshopper_order_item",
          "tableTo": "tonytonyshopper_order",
          "columnsFrom": [
            "orderId"
          ],
          "columnsTo": [
            "id"
          ],
          "onDelete": "cascade",
          "onUpdate": "no action"
        },
        "tonytonyshopper_order_item_productVariantId_tonytonyshopper_product_variant_id_fk": {
          "name": "tonytonyshopper_order_item_productVariantId_tonytonyshopper_product_variant_id_fk",
          "tableFrom": "tonytonyshopper_order_item",
          "tableTo": "tonytonyshopper_product_variant",
          "columnsFrom": [
            "productVariantId"
          ],
          "columnsTo": [
            "id"
          ],
          "onDelete": "no action",
          "onUpdate": "no action"
        }
      },
      "compositePrimaryKeys": {},
      "uniqueConstraints": {},
      "policies": {},
      "checkConstraints": {},
      "isRLSEnabled": false
    },
    "public.tonytonyshopper_order": {
      "name": "tonytonyshopper_order",
      "schema": "",
      "columns": {
        "id": {
          "name": "id",
          "type": "varchar(255)",
          "primaryKey": true,
          "notNull": true
        },
        "userId": {
          "name": "userId",
          "type": "varchar(255)",
          "primaryKey": false,
          "notNull": false
        },
        "guestEmail": {
          "name": "guestEmail",
          "type": "varchar(255)",
          "primaryKey": false,
          "notNull": false
        },
        "status": {
          "name": "status",
          "type": "order_status",
          "typeSchema": "public",
          "primaryKey": false,
          "notNull": true
        },
        "totalAmount": {
          "name": "totalAmount",
          "type": "numeric(10, 2)",
          "primaryKey": false,
          "notNull": true
        },
        "shipping_address": {
          "name": "shipping_address",
          "type": "json",
          "primaryKey": false,
          "notNull": false
        },
        "billing_address": {
          "name": "billing_address",
          "type": "json",
          "primaryKey": false,
          "notNull": false
        },
        "paymentIntentId": {
          "name": "paymentIntentId",
          "type": "varchar(255)",
          "primaryKey": false,
          "notNull": false
        },
        "carrier": {
          "name": "carrier",
          "type": "varchar(50)",
          "primaryKey": false,
          "notNull": false
        },
        "tracking_number": {
          "name": "tracking_number",
          "type": "varchar(255)",
          "primaryKey": false,
          "notNull": false
        },
        "createdAt": {
          "name": "createdAt",
          "type": "timestamp with time zone",
          "primaryKey": false,
          "notNull": false,
          "default": "CURRENT_TIMESTAMP"
        }
      },
      "indexes": {},
      "foreignKeys": {
        "tonytonyshopper_order_userId_tonytonyshopper_user_id_fk": {
          "name": "tonytonyshopper_order_userId_tonytonyshopper_user_id_fk",
          "tableFrom": "tonytonyshopper_order",
          "tableTo": "tonytonyshopper_user",
          "columnsFrom": [
            "userId"
          ],
          "columnsTo": [
            "id"
          ],
          "onDelete": "no action",
          "onUpdate": "no action"
        }
      },
      "compositePrimaryKeys": {},
      "uniqueConstraints": {
        "tonytonyshopper_order_paymentIntentId_unique": {
          "name": "tonytonyshopper_order_paymentIntentId_unique",
          "nullsNotDistinct": false,
          "columns": [
            "paymentIntentId"
          ]
        }
      },
      "policies": {},
      "checkConstraints": {},
      "isRLSEnabled": false
    },
    "public.tonytonyshopper_product_variant": {
      "name": "tonytonyshopper_product_variant",
      "schema": "",
      "columns": {
        "id": {
          "name": "id",
          "type": "varchar(255)",
          "primaryKey": true,
          "notNull": true
        },
        "productId": {
          "name": "productId",
          "type": "varchar(255)",
          "primaryKey": false,
          "notNull": true
        },
        "name": {
          "name": "name",
          "type": "varchar(255)",
          "primaryKey": false,
          "notNull": false
        },
        "price": {
          "name": "price",
          "type": "numeric(10, 2)",
          "primaryKey": false,
          "notNull": true
        },
        "images": {
          "name": "images",
          "type": "json",
          "primaryKey": false,
          "notNull": false
        },
        "stock": {
          "name": "stock",
          "type": "integer",
          "primaryKey": false,
          "notNull": true,
          "default": 0
        },
        "options": {
          "name": "options",
          "type": "json",
          "primaryKey": false,
          "notNull": false
        }
      },
      "indexes": {
        "variant_product_id_idx": {
          "name": "variant_product_id_idx",
          "columns": [
            {
              "expression": "productId",
              "isExpression": false,
              "asc": true,
              "nulls": "last"
            }
          ],
          "isUnique": false,
          "concurrently": false,
          "method": "btree",
          "with": {}
        }
      },
      "foreignKeys": {
        "tonytonyshopper_product_variant_productId_tonytonyshopper_product_id_fk": {
          "name": "tonytonyshopper_product_variant_productId_tonytonyshopper_product_id_fk",
          "tableFrom": "tonytonyshopper_product_variant",
          "tableTo": "tonytonyshopper_product",
          "columnsFrom": [
            "productId"
          ],
          "columnsTo": [
            "id"
          ],
          "onDelete": "cascade",
          "onUpdate": "no action"
        }
      },
      "compositePrimaryKeys": {},
      "uniqueConstraints": {},
      "policies": {},
      "checkConstraints": {},
      "isRLSEnabled": false
    },
    "public.tonytonyshopper_product": {
      "name": "tonytonyshopper_product",
      "schema": "",
      "columns": {
        "id": {
          "name": "id",
          "type": "varchar(255)",
          "primaryKey": true,
          "notNull": true
        },
        "name": {
          "name": "name",
          "type": "varchar(255)",
          "primaryKey": false,
          "notNull": true
        },
        "description": {
          "name": "description",
          "type": "text",
          "primaryKey": false,
          "notNull": false
        },
        "videos": {
          "name": "videos",
          "type": "json",
          "primaryKey": false,
          "notNull": false
        },
        "is_featured": {
          "name": "is_featured",
          "type": "boolean",
          "primaryKey": false,
          "notNull": true,
          "default": false
        },
        "averageRating": {
          "name": "averageRating",
          "type": "numeric(2, 1)",
          "primaryKey": false,
          "notNull": true,
          "default": "'0'"
        },
        "review_count": {
          "name": "review_count",
          "type": "integer",
          "primaryKey": false,
          "notNull": true,
          "default": 0
        },
        "minPrice": {
          "name": "minPrice",
          "type": "numeric(10, 2)",
          "primaryKey": false,
          "notNull": true,
          "default": "'0'"
        },
        "maxPrice": {
          "name": "maxPrice",
          "type": "numeric(10, 2)",
          "primaryKey": false,
          "notNull": true,
          "default": "'0'"
        },
        "total_stock": {
          "name": "total_stock",
          "type": "integer",
          "primaryKey": false,
          "notNull": true,
          "default": 0
        },
        "has_out_of_stock_variants": {
          "name": "has_out_of_stock_variants",
          "type": "boolean",
          "primaryKey": false,
          "notNull": true,
          "default": false
        },
        "createdAt": {
          "name": "createdAt",
          "type": "timestamp with time zone",
          "primaryKey": false,
          "notNull": false,
          "default": "CURRENT_TIMESTAMP"
        },
        "updatedAt": {
          "name": "updatedAt",
          "type": "timestamp with time zone",
          "primaryKey": false,
          "notNull": false
        }
      },
      "indexes": {},
      "foreignKeys": {},
      "compositePrimaryKeys": {},
      "uniqueConstraints": {},
      "policies": {},
      "checkConstraints": {},
      "isRLSEnabled": false
    },
    "public.tonytonyshopper_products_to_categories": {
      "name": "tonytonyshopper_products_to_categories",
      "schema": "",
      "columns": {
        "productId": {
          "name": "productId",
          "type": "varchar(255)",
          "primaryKey": false,
          "notNull": true
        },
        "categoryId": {
          "name": "categoryId",
          "type": "varchar(255)",
          "primaryKey": false,
          "notNull": true
        }
      },
      "indexes": {},
      "foreignKeys": {
        "tonytonyshopper_products_to_categories_productId_tonytonyshopper_product_id_fk": {
          "name": "tonytonyshopper_products_to_categories_productId_tonytonyshopper_product_id_fk",
          "tableFrom": "tonytonyshopper_products_to_categories",
          "tableTo": "tonytonyshopper_product",
          "columnsFrom": [
            "productId"
          ],
          "columnsTo": [
            "id"
          ],
          "onDelete": "cascade",
          "onUpdate": "no action"
        },
        "tonytonyshopper_products_to_categories_categoryId_tonytonyshopper_category_id_fk": {
          "name": "tonytonyshopper_products_to_categories_categoryId_tonytonyshopper_category_id_fk",
          "tableFrom": "tonytonyshopper_products_to_categories",
          "tableTo": "tonytonyshopper_category",
          "columnsFrom": [
            "categoryId"
          ],
          "columnsTo": [
            "id"
          ],
          "onDelete": "cascade",
          "onUpdate": "no action"
        }
      },
      "compositePrimaryKeys": {
        "tonytonyshopper_products_to_categories_productId_categoryId_pk": {
          "name": "tonytonyshopper_products_to_categories_productId_categoryId_pk",
          "columns": [
            "productId",
            "categoryId"
          ]
        }
      },
      "uniqueConstraints": {},
      "policies": {},
      "checkConstraints": {},
      "isRLSEnabled": false
    },
    "public.tonytonyshopper_session": {
      "name": "tonytonyshopper_session",
      "schema": "",
      "columns": {
        "sessionToken": {
          "name": "sessionToken",
          "type": "varchar(255)",
          "primaryKey": true,
          "notNull": true
        },
        "userId": {
          "name": "userId",
          "type": "varchar(255)",
          "primaryKey": false,
          "notNull": true
        },
        "expires": {
          "name": "expires",
          "type": "timestamp with time zone",
          "primaryKey": false,
          "notNull": true
        }
      },
      "indexes": {
        "t_user_id_idx": {
          "name": "t_user_id_idx",
          "columns": [
            {
              "expression": "userId",
              "isExpression": false,
              "asc": true,
              "nulls": "last"
            }
          ],
          "isUnique": false,
          "concurrently": false,
          "method": "btree",
          "with": {}
        }
      },
      "foreignKeys": {
        "tonytonyshopper_session_userId_tonytonyshopper_user_id_fk": {
          "name": "tonytonyshopper_session_userId_tonytonyshopper_user_id_fk",
          "tableFrom": "tonytonyshopper_session",
          "tableTo": "tonytonyshopper_user",
          "columnsFrom": [
            "userId"
          ],
          "columnsTo": [
            "id"
          ],
          "onDelete": "no action",
          "onUpdate": "no action"
        }
      },
      "compositePrimaryKeys": {},
      "uniqueConstraints": {},
      "policies": {},
      "checkConstraints": {},
      "isRLSEnabled": false
    },
    "public.tonytonyshopper_user": {
      "name": "tonytonyshopper_user",
      "schema": "",
      "columns": {
        "id": {
          "name": "id",
          "type": "varchar(255)",
          "primaryKey": true,
          "notNull": true
        },
        "name": {
          "name": "name",
          "type": "varchar(255)",
          "primaryKey": false,
          "notNull": false
        },
        "email": {
          "name": "email",
          "type": "varchar(255)",
          "primaryKey": false,
          "notNull": true
        },
        "emailVerified": {
          "name": "emailVerified",
          "type": "timestamp with time zone",
          "primaryKey": false,
          "notNull": false,
          "default": "CURRENT_TIMESTAMP"
        },
        "image": {
          "name": "image",
          "type": "varchar(255)",
          "primaryKey": false,
          "notNull": false
        },
        "role": {
          "name": "role",
          "type": "user_role",
          "typeSchema": "public",
          "primaryKey": false,
          "notNull": true,
          "default": "'user'"
        }
      },
      "indexes": {},
      "foreignKeys": {},
      "compositePrimaryKeys": {},
      "uniqueConstraints": {},
      "policies": {},
      "checkConstraints": {},
      "isRLSEnabled": false
    },
    "public.tonytonyshopper_verification_token": {
      "name": "tonytonyshopper_verification_token",
      "schema": "",
      "columns": {
        "identifier": {
          "name": "identifier",
          "type": "varchar(255)",
          "primaryKey": false,
          "notNull": true
        },
        "token": {
          "name": "token",
          "type": "varchar(255)",
          "primaryKey": false,
          "notNull": true
        },
        "expires": {
          "name": "expires",
          "type": "timestamp with time zone",
          "primaryKey": false,
          "notNull": true
        }
      },
      "indexes": {},
      "foreignKeys": {},
      "compositePrimaryKeys": {
        "tonytonyshopper_verification_token_identifier_token_pk": {
          "name": "tonytonyshopper_verification_token_identifier_token_pk",
          "columns": [
            "identifier",
            "token"
          ]
        }
      },
      "uniqueConstraints": {},
      "policies": {},
      "checkConstraints": {},
      "isRLSEnabled": false
    }
  },
  "enums": {
    "public.order_status": {
      "name": "order_status",
      "schema": "public",
      "values": [
        "pending",
        "cancelled",
        "paid",
        "shipped"
      ]
    },
    "public.user_role": {
      "name": "user_role",
      "schema": "public",
      "values": [
        "user",
        "admin"
      ]
    }
  },
  "schemas": {},
  "sequences": {},
  "roles": {},
  "policies": {},
  "views": {},
  "_meta": {
    "columns": {},
    "schemas": {},
    "tables": {}
  }
}